{"version":"0.1.0","name":"landing-page-mhsolution","dependencies":{"@reduxjs/toolkit":{"version":"1.6.2"},"@svgr/webpack":{"version":"6.0.0"},"aos":{"version":"2.3.4"},"axios":{"version":"0.24.0"},"bootstrap":{"version":"5.1.3"},"html-react-parser":{"version":"1.4.0"},"next":{"version":"10.2.3"},"react-bootstrap":{"version":"2.0.0"},"react-dom":{"version":"17.0.2"},"react-dropzone":{"version":"11.4.2"},"react-html-parser":{"version":"2.0.2"},"react-redux":{"version":"7.2.6"},"react-transition-group":{"version":"4.4.2"},"react":{"version":"17.0.2"},"sass":{"version":"1.43.3"},"swiper":{"version":"6.8.4"}}}